{
    "login_title": "Anmelden",
    "welcome_back": "Willkommen zurück!",
    "email": "E-Mail",
    "password": "Passwort",
    "email_required": "E-Mail wird benötigt",
    "password_required": "Passwort wird benötigt",
    "login_button": "Einloggen",
    "register_prompt": "Haben Sie noch kein Konto? Registrieren",
    "forgot_password": "Passwort vergessen?",
    "register_title": "Registrieren Sie Ihr Konto",
    "create_account": "Konto erstellen",
    "username": "Benutzername",
    "username_required": "Benutzername wird benötigt",
    "registered_successfully": "Erfolgreich registriert",
    "register": "Registrieren",
    "already_have_account": "Haben Sie bereits ein Konto? Einloggen",
    "google_sign_up": "Mit Google anmelden",
    "google_sign_in_success": "Erfolgreich mit Google angemeldet",
    "google_sign_in_failed": "Google-Anmeldung fehlgeschlagen",
    "logout": "Abmelden",
    "logout_confirm": "Möchten Sie sich wirklich abmelden?",
    "yes": "Ja",
    "no": "Nein",
    "home_title": "Startseite",
    "dashboard": "Übersicht",
    "profile": "Profil",
    "settings": "Einstellungen",
    "update_profile": "Profil aktualisieren",
    "save_changes": "Änderungen speichern",
    "update_successful": "Profil erfolgreich aktualisiert",
    "language": "Sprache",
    "dark_mode": "Dunkelmodus",
    "light_mode": "Hellmodus",
    "search": "Suche",
    "no_results_found": "Keine Ergebnisse gefunden",
    "error_occurred": "Ein Fehler ist aufgetreten. Bitte versuchen Sie es erneut.",
    "retry": "Erneut versuchen",
    "delete_account": "Konto löschen",
    "delete_account_confirm": "Möchten Sie Ihr Konto wirklich löschen? Diese Aktion ist unwiderruflich.",
    "account_deleted": "Ihr Konto wurde erfolgreich gelöscht.",
    "notifications": "Benachrichtigungen",
    "mark_as_read": "Als gelesen markieren",
    "clear_all": "Alles löschen",
    "about_us": "Über uns",
    "contact_us": "Kontaktieren Sie uns",
    "privacy_policy": "Datenschutzrichtlinie",
    "terms_of_service": "Nutzungsbedingungen",
    "version": "Version",
    "loading": "Laden...",
    "upload": "Hochladen",
    "download": "Herunterladen",
    "file_size_limit": "Dateigrößenlimit überschritten",
    "success": "Erfolg",
    "failed": "Fehlgeschlagen",
    "try_again": "Erneut versuchen",
    "how_to_use_title": "Benutzung",
    "how_to_use_voice_title": "Sprachfunktion",
    "how_to_use_voice_description": "Erfahren Sie, wie Sie die Sprachfunktion zur Interaktion mit der App verwenden.",
    "how_to_use_voice": "Sprachbefehle aktivieren.",
    "how_to_use_history_title": "Verlauf",
    "how_to_use_history_description": "Greifen Sie auf den Verlauf der App-Nutzung zu und sehen Sie ihn sich an.",
    "how_to_use_history": "Sehen Sie sich Ihren Verlauf an.",
    "how_to_use_connection_title": "Verbindung",
    "how_to_use_connection_description": "Stellen Sie eine Verbindung zu anderen Benutzern oder Geräten her.",
    "how_to_use_connection": "Mit Freunden oder Geräten verbinden.",
    "how_to_use_favorite_title": "Favoriten",
    "how_to_use_favorite_description": "Markieren Sie Elemente oder Personen als Favoriten für den einfachen Zugriff.",
    "how_to_use_favorite": "Zu Favoriten hinzufügen.",
    "how_to_use_settings_title": "Einstellungen",
    "how_to_use_settings_description": "Verwalten Sie die App-Einstellungen und -Präferenzen.",
    "how_to_use_settings": "Einstellungen anpassen.",
    "registration_failed": "Registrierung fehlgeschlagen"
}